yclientsapi/__init__.py
yclientsapi/components/activity.py
yclientsapi/components/auth.py
yclientsapi/components/duplication.py
yclientsapi/components/record.py
yclientsapi/components/salary.py
yclientsapi/components/service.py
yclientsapi/components/service_category.py
yclientsapi/components/staff.py
yclientsapi/components/storage.py
yclientsapi/config.py
yclientsapi/exceptions.py
yclientsapi/headers.py
yclientsapi/logger.py
yclientsapi/py.typed
yclientsapi/schema/activity.py
yclientsapi/schema/auth.py
yclientsapi/schema/duplication.py
yclientsapi/schema/record.py
yclientsapi/schema/salary.py
yclientsapi/schema/service.py
yclientsapi/schema/service_category.py
yclientsapi/schema/staff.py
yclientsapi/schema/storage.py
yclientsapi/schema/webhook.py
yclientsapi/sender.py
yclientsapi/tests/README.md
yclientsapi/tests/integration/.env.example
yclientsapi/tests/integration/conftest.py
yclientsapi/tests/integration/src/fixtures/fixt_activity.py
yclientsapi/tests/integration/src/fixtures/fixt_duplication.py
yclientsapi/tests/integration/src/fixtures/fixt_lib.py
yclientsapi/tests/integration/src/fixtures/fixt_service_category.py
yclientsapi/tests/integration/src/test_data/activity.py
yclientsapi/tests/integration/src/test_data/duplication.py
yclientsapi/tests/integration/src/test_data/record.py
yclientsapi/tests/integration/src/test_data/salary.py
yclientsapi/tests/integration/src/test_data/service_category.py
yclientsapi/tests/integration/src/tests/test_activity.py
yclientsapi/tests/integration/src/tests/test_auth.py
yclientsapi/tests/integration/src/tests/test_duplication.py
yclientsapi/tests/integration/src/tests/test_record.py
yclientsapi/tests/integration/src/tests/test_salary.py
yclientsapi/tests/integration/src/tests/test_service.py
yclientsapi/tests/integration/src/tests/test_service_category.py
yclientsapi/tests/integration/src/tests/test_staff.py
yclientsapi/tests/integration/vars.py
yclientsapi/tools.py
poor_yclientsapi-0.1.22.dist-info/METADATA
poor_yclientsapi-0.1.22.dist-info/WHEEL
poor_yclientsapi-0.1.22.dist-info/licenses/LICENSE
poor_yclientsapi-0.1.22.dist-info/RECORD
