Metadata-Version: 2.4
Name: poor_yclientsapi
Version: 0.1.22
Summary: Poor collection of API methods for Yclients app
License: MIT
License-File: LICENSE
Author: Maksim Kosinov
Author-email: mkosinov@mail.ru
Requires-Python: >=3.12,<4.0
Classifier: License :: OSI Approved :: MIT License
Classifier: Programming Language :: Python :: 3
Classifier: Programming Language :: Python :: 3.12
Classifier: Programming Language :: Python :: 3.13
Classifier: Programming Language :: Python :: 3.14
Requires-Dist: httpx (>=0.27.2,<0.28.0)
Requires-Dist: orjson (>=3.10.7,<4.0.0)
Requires-Dist: pydantic (>=2.9.1,<3.0.0)
Requires-Dist: python-dotenv (>=1.0.1,<2.0.0)
Project-URL: Repository, https://github.com/mkosinov/yclientsapi
